AUTHORS.rst
CONTRIBUTING.rst
HISTORY.rst
LICENSE
MANIFEST.in
README.rst
setup.cfg
setup.py
docs/Makefile
docs/authors.rst
docs/conf.py
docs/contributing.rst
docs/history.rst
docs/index.rst
docs/installation.rst
docs/make.bat
docs/modules.rst
docs/mprofi_api_client.rst
docs/readme.rst
mprofi_api_client/__init__.py
mprofi_api_client/connector.py
mprofi_api_client.egg-info/PKG-INFO
mprofi_api_client.egg-info/SOURCES.txt
mprofi_api_client.egg-info/dependency_links.txt
mprofi_api_client.egg-info/not-zip-safe
mprofi_api_client.egg-info/top_level.txt
mprofi_api_client/packages/__init__.py
mprofi_api_client/packages/requests/__init__.py
mprofi_api_client/packages/requests/adapters.py
mprofi_api_client/packages/requests/api.py
mprofi_api_client/packages/requests/auth.py
mprofi_api_client/packages/requests/certs.py
mprofi_api_client/packages/requests/compat.py
mprofi_api_client/packages/requests/cookies.py
mprofi_api_client/packages/requests/exceptions.py
mprofi_api_client/packages/requests/hooks.py
mprofi_api_client/packages/requests/models.py
mprofi_api_client/packages/requests/sessions.py
mprofi_api_client/packages/requests/status_codes.py
mprofi_api_client/packages/requests/structures.py
mprofi_api_client/packages/requests/utils.py
mprofi_api_client/packages/requests/packages/__init__.py
mprofi_api_client/packages/requests/packages/chardet/__init__.py
mprofi_api_client/packages/requests/packages/chardet/big5freq.py
mprofi_api_client/packages/requests/packages/chardet/big5prober.py
mprofi_api_client/packages/requests/packages/chardet/chardetect.py
mprofi_api_client/packages/requests/packages/chardet/chardistribution.py
mprofi_api_client/packages/requests/packages/chardet/charsetgroupprober.py
mprofi_api_client/packages/requests/packages/chardet/charsetprober.py
mprofi_api_client/packages/requests/packages/chardet/codingstatemachine.py
mprofi_api_client/packages/requests/packages/chardet/compat.py
mprofi_api_client/packages/requests/packages/chardet/constants.py
mprofi_api_client/packages/requests/packages/chardet/cp949prober.py
mprofi_api_client/packages/requests/packages/chardet/escprober.py
mprofi_api_client/packages/requests/packages/chardet/escsm.py
