Metadata-Version: 1.1
Name: mprofi-api-client
Version: 0.1.3
Summary: Python Client library for mProfi REST API
Home-page: https://github.com/materna/mprofi_api_client_python
Author: Materna Communications Sp. z o.o.
Author-email: pomoc@materna.com.pl
License: Apache
Keywords: mprofi,api,client
Platform: UNKNOWN
Classifier: Development Status :: 4 - Beta
Classifier: Intended Audience :: Developers
Classifier: Intended Audience :: System Administrators
Classifier: Intended Audience :: Telecommunications Industry
Classifier: License :: OSI Approved :: Apache Software License
Classifier: Natural Language :: English
Classifier: Programming Language :: Python :: 2
Classifier: Programming Language :: Python :: 2.7
